ragic/__init__.py
ragic/client.py
ragic/types.py
python_ragic-0.3.2.dist-info/LICENSE
python_ragic-0.3.2.dist-info/METADATA
python_ragic-0.3.2.dist-info/WHEEL
python_ragic-0.3.2.dist-info/top_level.txt
python_ragic-0.3.2.dist-info/RECORD
