Metadata-Version: 2.1
Name: python-ragic
Version: 0.3.2
Summary: Python Ragic API client for data loading and manipulation.
Author: jonah_whaler_2348
Author-email: jk_saga@proton.me
License: GPLv3
Keywords: ragic,data loader
Classifier: Development Status :: 1 - Planning
Classifier: Intended Audience :: Developers
Classifier: License :: OSI Approved :: GNU General Public License v3 (GPLv3)
Classifier: Programming Language :: Python :: 3.10
License-File: LICENSE
Requires-Dist: python-dotenv==0.21.0
Requires-Dist: PyYAML==6.0.2
Requires-Dist: httpx[http2]==0.28.1
Requires-Dist: h2==4.2.0
